{"name":"Sau Khi Nổi Tiếng, Đại Lão Hào Môn Trở Thành Fan Đầu Tàu Của Tôi!","folder":"saukhinoitiengdjailaohaomontrothanhfandjautaucuatoi","tacGia":"Nhạn Phi Hành","theLoai":"Đam Mỹ","trangThai":"Đang ra","description":"<strong>Văn án</strong><br><br>Bởi vì cơ thể yếu ớt nên từ nhỏ Giang Phóng đã bị người nhà đưa lên chùa làm hòa thượng, sau đó anh lại bị lão hòa thượng đuổi về nhà, trùng hợp lúc này em trai thực tập sinh vừa debut của anh đang chuẩn bị tham gia một chương trình giải trí, cần mời một người thân trong gia đình quay cùng.<br><br>Vì nể mặt tiền nên Giang Phóng đã đồng ý tham gia, ai ngờ em trai lại có thể chất “hot search bôi xấu”, tin tức hai anh em tham gia chương trình vừa truyền lên trên mạng thì…&nbsp;<br><br>Antifan: Tại sao mấy người học vấn thấp cũng có thể quay chương trình thực tế được vậy, lần này vua cọ Giang Tề sợ một người không đủ nên định rủ thêm anh trai tạo thành nhóm ăn vạ sao?<br><br>Giang • có biệt danh hot boy học thần cao ngạo lãnh đạm • Phóng:????<br><br>Hình như mấy người không biết thế nào là ăn vạ, cái loại mà bị khuyết tật đấy.<br><br>Sau khi chương trình bắt đầu quay:<br><br>“Đệch mợ, sao không ai nói với tôi anh trai Giang Tề có diện mạo như vậy, giá trị nhan sắc này là động lực khiến tôi có thể liếm hư màn hình của bất kỳ chiếc điện thoại nào!”<br><br>“Tôi hoa mắt à? Vì sao tôi lại nhìn thấy hot boy trường mình trên chương trình giải trí chứ?”<br><br>“Mấy người nghiêm túc hả, nói Giang Phóng có học vấn thấp, có biết học thần của đại học Yến là ai không?”<br><br>***<br><br>Giang Phóng vốn chỉ muốn kiếm tiền làm dự án khởi nghiệp, không ngờ rằng sau khi gia nhập giới giải trí lại trở nên cực hot, thành công thu hoạch được một vị fan đại gia cùng với chín mươi chín tin nhắn đe dọa của antifan giấu mặt.<br><br>Đại gia Trình Tứ: Đợi gửi thêm một tin nhắn nữa.<br><br>Giang Phóng:?<br><br>Đại gia Trình Tứ: Chẵn một trăm rồi đưa lên đường luôn.<br><br>Giang Phóng: Sẵn tay rải chút giấy tiền vàng bạc, lên đường bình an.<br><br>***<br><br>Cả Trình gia bị kinh động vì em gái Trình Tứ tiêu hết cả triệu nhân dân tệ cho một minh tinh nào đó, ba mẹ Trình lo sợ con gái sẽ bị lừa nên bảo Trình Tứ trông nom em gái hơn.<br><br>Trong quá trình giám sát, Trình Tứ đã học được cách đánh dấu đua top cho idol, tiếp ứng cho idol, dùng tiền để tăng doanh số, đồng thời còn học được cách biển thủ bạc công nữa.<br><br>Em gái: Giám sát em như đã nói đi đâu rồi, tại sao anh lại thành fan đầu tàu&nbsp;<em><strong>(1)</strong></em>&nbsp;của idol em?<br><br>- ------------------------------<br><br><strong>Couple:</strong>&nbsp;Bên ngoài là học thần lãnh đạm nhưng thật ra bên trong đầy ý xấu thụ X Bên ngoài là tổng tài bá đạo nhưng thật ra bên trong là lão cán bộ công&nbsp;<em><strong>(2)</strong></em>.<br><br><strong>Tóm tắt nội dung trong một câu:</strong>&nbsp;Người ưu tú thì nhất định sẽ có người yêu thích.<br><br><strong>Lập ý:</strong>&nbsp;Nói không với bạo lực mạng, nói không với anh hùng bàn phím.<br><br><strong>Tóm tắt nội dung trong nhiều câu:</strong>&nbsp;Giang Phóng là cao tài sinh&nbsp;<strong><em>(3)</em></strong>&nbsp;của đại học Yến, bởi vì thiếu kinh phí để làm thực nghiệm nên đã đồng ý tham gia chương trình giải trí cùng em trai thực tập sinh vừa debut, sau đó trong lúc quay chương trình vì giúp em trai giải quyết chuyện cọ nhiệt cùng tạo scandal của các idol khác mà trở nên nổi tiếng. Lại ngoài ý muốn kết bạn với Trình Tứ, phát hiện lúc nhỏ hắn cũng không được ba mẹ quan tâm giống mình nên hai người rất thưởng thức lẫn nhau, sinh ra cộng hưởng, cũng dưới sự trợ giúp của Trình Tứ mà Giang Phóng có thể yên tâm làm thực nghiệm.<br>Tác phẩm này có nhịp điệu lưu loát không gò bó, nhạc dạo ấm áp, sau khi nhân vật chính ý thức được ba mẹ cũng có nỗi khổ riêng, em trai cũng sống không dễ dàng thì buông xuống vướng mắc trong lòng, làm hòa với gia đình, nhân vật chính thông minh nhưng không kiêu ngạo, gặp khó khăn tuyệt đối không lùi bước, có mục tiêu kiên định, cũng vì điều đó mà nỗ lực tiến tới.<br><br>...<br><br><em>(1)&nbsp;Fan đầu tàu [粉头]: (Hay còn gọi là kỹ nữ) Dùng để chỉ người đứng đầu trong fandom của một idol nào đó. Muốn xây dựng một fandom hoàn chỉnh thì một fan đầu tàu có kinh nghiệm phong phú là điều không thể thiếu. Fan đầu tàu thường là người thân, bạn bè, nhân viên đoàn đội của idol hoặc là một fan hâm mộ có kinh tế vững vàng cùng năng lực tổ chức mạnh mẽ. Fan đầu tàu có nhiệm vụ giúp idol xử lý các hoạt động với fan hâm mộ, thậm chí là giúp idol gom góp tài chính.</em><br><em>(2) Lão cán bộ: Là từ thịnh hành trên mạng xã hội của Trung Quốc, chỉ những người đàn ông có cuộc sống giản dị, kín đáo, có yêu cầu nghiêm khắc với bản thân.</em><br><br><em>(3) Cao tài sinh [高材生]: Chỉ người thông qua sự nỗ lực ở những phương diện nào đó mà đạt được thành tích vượt trội. Đặc biệt là trong khía cạnh học tập.&nbsp;</em>"}