{"name":"Nữ Trang Đại Lão Công Lược Sổ Tay","folder":"nutrangdjailaocongluocsotay","tacGia":"Lãnh Sơn Nguyệt","theLoai":"Tiên Hiệp","trangThai":"Đang ra","description":"Khi xuyên qua đến vai chính nghèo túng, Nguyễn Cẩm Bạch không có bất kỳ hạnh phúc nào, chỉ được đóng gói và đưa vai chính đi. Từ đó, anh ta không còn sợ ngày sau người ta phi thăng xưng vương xưng đế, mà chỉ muốn trở thành đệ tử của Nguyên Cẩm.<br><br>Với sự giúp đỡ của nữ trang đại lão Nguyễn Cẩm Bạch, Khương Tiếu Uyên đã có thể bắt đầu hành trình tu luyện. Nhưng sau khi được trọng sinh, anh ta lại phải ngự trị với ký ức về nam chủ cũ.<br><br>Sau một khoảng thời gian đấu tranh tư tưởng, Khương Tiếu Uyên đã tìm được cách đạt được mục tiêu với sự giúp đỡ của Nguyễn Cẩm Bạch. Tuy nhiên, khi bị dẫn dắt bởi bản năng, anh ta đã nói một điều khiến cho Nguyễn Cẩm Bạch giận dữ.<br><br>Tuy nhiên, với tài năng của mình, Nguyễn Cẩm Bạch đã giúp Khương Tiếu Uyên vượt qua những khó khăn để trở thành một chiến binh tài ba. Với cá tính mạnh mẽ và phẩm chất tuyệt vời, Nguyễn và Khương đã trở thành một cặp đôi đẹp đôi."}